terndata/flux/__init__.py
terndata/flux/export_utils.py
terndata/flux/flux_api.py
terndata/flux/plot.py
terndata/flux/py.typed
terndata/flux/utils.py
terndata/flux/version.py
terndata_flux-1.0.5.dist-info/licenses/LICENSE
terndata_flux-1.0.5.dist-info/licenses/NOTICE
terndata_flux-1.0.5.dist-info/METADATA
terndata_flux-1.0.5.dist-info/WHEEL
terndata_flux-1.0.5.dist-info/top_level.txt
terndata_flux-1.0.5.dist-info/RECORD
