Metadata-Version: 2.4
Name: terndata.flux
Version: 1.0.5
Summary: TERN flux data access library
Author-email: "Terrestrial Ecosystem Research Network (TERN)" <esupprt@tern.org.au>
Maintainer-email: Yong Liaw <y.liaw@uq.edu.au>
License-Expression: Apache-2.0
Project-URL: Home, https://github.com/ternaustralia/terndata.flux
Project-URL: Documentation, https://terndata-flux.readthedocs.io
Classifier: Development Status :: 5 - Production/Stable
Classifier: Intended Audience :: Education
Classifier: Intended Audience :: Science/Research
Classifier: Programming Language :: Python
Classifier: Programming Language :: Python :: 3
Classifier: Programming Language :: Python :: 3.10
Classifier: Programming Language :: Python :: 3.11
Classifier: Programming Language :: Python :: 3.12
Classifier: Programming Language :: Python :: 3.13
Classifier: Topic :: Software Development :: Libraries :: Python Modules
Requires-Python: >=3.10
License-File: LICENSE
License-File: NOTICE
Requires-Dist: typing-extensions
Requires-Dist: xarray
Requires-Dist: numpy
Requires-Dist: pandas
Requires-Dist: geopandas
Requires-Dist: netCDF4
Requires-Dist: requests
Requires-Dist: python-dateutil
Requires-Dist: pytz
Requires-Dist: xlrd
Requires-Dist: xlsxwriter
Requires-Dist: defusedxml
Requires-Dist: matplotlib
Dynamic: license-file
